reprisal/__init__.py
reprisal/__main__.py
reprisal/cli.py
reprisal/constants.py
reprisal/py.typed
reprisal-0.0.1.dist-info/LICENSE
reprisal-0.0.1.dist-info/METADATA
reprisal-0.0.1.dist-info/WHEEL
reprisal-0.0.1.dist-info/entry_points.txt
reprisal-0.0.1.dist-info/RECORD
